<!DOCTYPE VNCLASS SYSTEM "vn_class-3.dtd">
<VNCLASS ID="cost-54.2" xmlns:xsi="http://www.w3.org/2001/XMLSchema-instance" xsi:noNamespaceSchemaLocation="vn_schema-3.xsd">
 <MEMBERS>
  <MEMBER fn_mapping="Bringing" grouping="carry.02" name="carry" verbnet_key="carry#2" wn="?carry%2:42:13" features=""/>
  <MEMBER fn_mapping="Expensiveness" grouping="cost.01" name="cost" verbnet_key="cost#1" wn="cost%2:42:00" features=""/>
  <MEMBER fn_mapping="None" grouping="last.01" name="last" verbnet_key="last#1" wn="last%2:42:00" features=""/>
  <MEMBER fn_mapping="None" grouping="net.01" name="net" verbnet_key="net#1" wn="net%2:40:01" features=""/>
  <MEMBER fn_mapping="Taking_time" grouping="take.03" name="take" verbnet_key="take#6" wn="take%2:40:06" features=""/>
 </MEMBERS>
 <THEMROLES>
  <THEMROLE type="Theme">
   <SELRESTRS>
    <SELRESTR Value="+" type="concrete"/>
   </SELRESTRS>
  </THEMROLE>
  <THEMROLE type="Value">
   <SELRESTRS/>
  </THEMROLE>
  <THEMROLE type="Beneficiary">
   <SELRESTRS logic="or">
    <SELRESTR Value="+" type="animate"/>
    <SELRESTR Value="+" type="organization"/>
   </SELRESTRS>
  </THEMROLE>
 </THEMROLES>
 <FRAMES>
  <FRAME>
   <DESCRIPTION descriptionNumber="0.2" primary="NP V NP.value" secondary="Transitive; Attribute Object" xtag=""/>
   <EXAMPLES>
    <EXAMPLE>
     The book cost $10.
    </EXAMPLE>
   </EXAMPLES>
   <SYNTAX>
    <NP value="Theme">
     <SYNRESTRS/>
    </NP>
    <VERB/>
    <NP value="Value">
     <SYNRESTRS/>
    </NP>
   </SYNTAX>
   <SEMANTICS>
    <PRED value="has_value">
     <ARGS>
      <ARG type="Event" value="E"/>
      <ARG type="ThemRole" value="Theme"/>
      <ARG type="PredSpecific" value="Attribute"/>
      <ARG type="ThemRole" value="Value"/>
     </ARGS>
    </PRED>
   </SEMANTICS>
  </FRAME>
  <FRAME>
   <DESCRIPTION descriptionNumber="" primary="NP V NP NP" secondary="NP-NP" xtag=""/>
   <EXAMPLES>
    <EXAMPLE>
     The bill cost them 500 million dollars.
    </EXAMPLE>
   </EXAMPLES>
   <SYNTAX>
    <NP value="Theme">
     <SYNRESTRS/>
    </NP>
    <VERB/>
    <NP value="Beneficiary">
     <SYNRESTRS/>
    </NP>
    <NP value="Value">
     <SYNRESTRS/>
    </NP>
   </SYNTAX>
   <SEMANTICS>
    <PRED value="has_value">
     <ARGS>
      <ARG type="Event" value="E"/>
      <ARG type="ThemRole" value="Theme"/>
      <ARG type="PredSpecific" value="Attribute"/>
      <ARG type="ThemRole" value="Value"/>
     </ARGS>
    </PRED>
    <PRED value="benefit">
     <ARGS>
      <ARG type="Event" value="E"/>
      <ARG type="ThemRole" value="Beneficiary"/>
     </ARGS>
    </PRED>
   </SEMANTICS>
  </FRAME>
 </FRAMES>
 <SUBCLASSES/>
</VNCLASS>